Metadata-Version: 2.1
Name: dfa-wrapper
Version: 0.0.1
Summary: Zerion Dataflow Automation API Wrapper
Home-page: https://github.com/jhsu98/dfa-wrapper
Author: Jonathan Hsu
Author-email: jhsu@zerionsoftware.com
License: MIT
Platform: UNKNOWN
Requires-Python: >=3.0
